gino_admin/__init__.py
gino_admin/auth.py
gino_admin/cli.py
gino_admin/config.py
gino_admin/core.py
gino_admin/history.py
gino_admin/routes/crud.py
gino_admin/routes/logic.py
gino_admin/routes/main.py
gino_admin/routes/rest.py
gino_admin/static/app.css
gino_admin/static/favicon.ico
gino_admin/templates/add_form.html
gino_admin/templates/app.html
gino_admin/templates/base.html
gino_admin/templates/data_table.html
gino_admin/templates/file_upload.html
gino_admin/templates/footer.html
gino_admin/templates/header.html
gino_admin/templates/history.html
gino_admin/templates/index.html
gino_admin/templates/init_db.html
gino_admin/templates/login.html
gino_admin/templates/modals/deepcopy_modal.html
gino_admin/templates/modals/delete_modal.html
gino_admin/templates/model_view.html
gino_admin/templates/presets.html
gino_admin/templates/settings.html
gino_admin/templates/sql_runner.html
gino_admin/templates/table_control_items.html
gino_admin/types.py
gino_admin/users.py
gino_admin/utils.py
gino_admin-0.3.0.dist-info/entry_points.txt
gino_admin-0.3.0.dist-info/LICENSE
gino_admin-0.3.0.dist-info/WHEEL
gino_admin-0.3.0.dist-info/METADATA
gino_admin-0.3.0.dist-info/RECORD
