Metadata-Version: 2.1
Name: gino-admin
Version: 0.3.0
Summary: Admin Panel for PostgreSQL DB with Gino ORM
Home-page: https://github.com/xnuinside/gino-admin
License: MIT
Author: xnuinside
Author-email: xnuinside@gmail.com
Requires-Python: >=3.7,<4.0
Classifier: License :: OSI Approved :: MIT License
Classifier: Programming Language :: Python :: 3
Classifier: Programming Language :: Python :: 3.7
Classifier: Programming Language :: Python :: 3.8
Classifier: Programming Language :: Python :: 3.9
Requires-Dist: PyYAML (>=5.3.1,<6.0.0)
Requires-Dist: Sanic-Jinja2 (>=2021.12.25,<2022.0.0)
Requires-Dist: aiofiles (>=0.6.0,<0.7.0)
Requires-Dist: click (>=7.1.2,<8.0.0)
Requires-Dist: dsnparse (>=0.1.15,<0.2.0)
Requires-Dist: expiring-dict (>=1.1.0,<2.0.0)
Requires-Dist: gino (>=1.0.1,<2.0.0)
Requires-Dist: passlib (>=1.7.4,<2.0.0)
Requires-Dist: pydantic (>=1.5.1,<2.0.0)
Requires-Dist: sanic (>=21.3.2,<22.0.0)
Requires-Dist: sanic-jwt (>=1.6.0,<2.0.0)
Requires-Dist: sqlalchemy_utils (>=0.36.8,<0.37.0)
Project-URL: Repository, https://github.com/xnuinside/gino-admin
